Metadata-Version: 2.1
Name: cursofiap-heliojunior
Version: 1.0.0
Summary: Descricao da sua lib cursofiap
Home-page: https://github.com/tadrianonet/cursofiap
Author: Francisco Helio 
Author-email: seu.email@example.com
License: MIT
